delta_lake_utils-1.0.0.dist-info/licenses/LICENSE
delta_utils/__init__.py
delta_utils/catalog_auditor.py
delta_utils/cli.py
delta_utils/health_checker.py
delta_utils/medallion_generator.py
delta_utils/optimizer.py
delta_utils/profiler.py
delta_utils/utils.py
delta_lake_utils-1.0.0.dist-info/METADATA
delta_lake_utils-1.0.0.dist-info/WHEEL
delta_lake_utils-1.0.0.dist-info/entry_points.txt
delta_lake_utils-1.0.0.dist-info/top_level.txt
delta_lake_utils-1.0.0.dist-info/RECORD
