Metadata-Version: 2.4
Name: delta-lake-utils
Version: 1.0.0
Summary: Production-grade utilities for Delta Lake management
Home-page: https://github.com/panwarnalini-hub/delta-lake-utils
Author: Nalini Panwar
Author-email: panwarnalini@gmail.com
Classifier: Programming Language :: Python :: 3.8
Classifier: Programming Language :: Python :: 3.9
Classifier: Programming Language :: Python :: 3.10
Classifier: License :: OSI Approved :: MIT License
Requires-Python: >=3.8
License-File: LICENSE
Requires-Dist: pyspark>=3.2.0
Requires-Dist: delta-spark>=2.0.0
Requires-Dist: click>=8.0.0
Requires-Dist: pandas>=1.3.0
Dynamic: author
Dynamic: author-email
Dynamic: classifier
Dynamic: description
Dynamic: description-content-type
Dynamic: home-page
Dynamic: license-file
Dynamic: requires-dist
Dynamic: requires-python
Dynamic: summary
